main.py
mseep_pymcp-0.1.1.dist-info/METADATA
mseep_pymcp-0.1.1.dist-info/WHEEL
mseep_pymcp-0.1.1.dist-info/entry_points.txt
mseep_pymcp-0.1.1.dist-info/top_level.txt
mseep_pymcp-0.1.1.dist-info/RECORD
