Metadata-Version: 2.4
Name: mseep-pymcp
Version: 0.1.1
Summary: Add your description here
Author-email: mseep <support@skydeck.ai>
Requires-Python: >=3.13
Requires-Dist: fastmcp>=2.2.5
Requires-Dist: mysql-connector-python>=9.3.0
Requires-Dist: requests>=2.32.3
